mypy_upgrade/__about__.py
mypy_upgrade/__init__.py
mypy_upgrade/__main__.py
mypy_upgrade/cli.py
mypy_upgrade/editing.py
mypy_upgrade/filter.py
mypy_upgrade/logging.py
mypy_upgrade/parsing.py
mypy_upgrade/py.typed
mypy_upgrade/silence.py
mypy_upgrade/utils.py
mypy_upgrade-0.0.1b6.dist-info/METADATA
mypy_upgrade-0.0.1b6.dist-info/WHEEL
mypy_upgrade-0.0.1b6.dist-info/entry_points.txt
mypy_upgrade-0.0.1b6.dist-info/licenses/AUTHORS.md
mypy_upgrade-0.0.1b6.dist-info/licenses/LICENSE.txt
mypy_upgrade-0.0.1b6.dist-info/RECORD
