Metadata-Version: 2.1
Name: mypy-upgrade
Version: 0.0.1b6
Summary: automatic error suppression for mypy
Project-URL: Changelog, https://github.com/ugognw/mypy-upgrade/blob/main/CHANGELOG.md
Project-URL: Documentation, https://github.com/ugognw/mypy-upgrade#readme
Project-URL: Issues, https://github.com/ugognw/mypy-upgrade/issues
Project-URL: Source, https://github.com/ugognw/mypy-upgrade
Author-email: Ugochukwu Nwosu <ugognw@gmail.com>
License: MIT License
License-File: AUTHORS.md
License-File: LICENSE.txt
Keywords: type checking
Classifier: Development Status :: 4 - Beta
Classifier: Intended Audience :: Developers
Classifier: Programming Language :: Python
Classifier: Programming Language :: Python :: 3.7
Classifier: Programming Language :: Python :: 3.8
Classifier: Programming Language :: Python :: 3.9
Classifier: Programming Language :: Python :: 3.10
Classifier: Programming Language :: Python :: 3.11
Classifier: Programming Language :: Python :: 3.12
Classifier: Programming Language :: Python :: 3.13
Classifier: Programming Language :: Python :: Implementation :: CPython
Classifier: Topic :: Software Development
Requires-Python: >=3.7
Requires-Dist: typing-extensions; python_version < '3.8'
